async_lru.cpython-314-darwin.so
async_lru_threadsafe-2.0.5.dist-info/RECORD
async_lru_threadsafe-2.0.5.dist-info/WHEEL
async_lru_threadsafe-2.0.5.dist-info/top_level.txt
async_lru_threadsafe-2.0.5.dist-info/METADATA
async_lru_threadsafe-2.0.5.dist-info/licenses/LICENSE
async_lru/__init__.py
async_lru/py.typed
