Metadata-Version: 2.4
Name: async-lru-threadsafe
Version: 2.0.5
Summary: A faster fork of async-lru: Simple threadsafe LRU cache for asyncio. Implemented in C.
Home-page: https://github.com/aio-libs/async-lru
License: MIT License
Project-URL: Chat: Matrix, https://matrix.to/#/#aio-libs:matrix.org
Project-URL: Chat: Matrix Space, https://matrix.to/#/#aio-libs-space:matrix.org
Project-URL: CI: GitHub Actions, https://github.com/aio-libs/async-lru/actions
Project-URL: GitHub: repo, https://github.com/aio-libs/async-lru
Keywords: asyncio,lru,lru_cache
Classifier: License :: OSI Approved :: MIT License
Classifier: Intended Audience :: Developers
Classifier: Programming Language :: Python
Classifier: Programming Language :: Python :: 3
Classifier: Programming Language :: Python :: 3 :: Only
Classifier: Programming Language :: Python :: 3.10
Classifier: Programming Language :: Python :: 3.11
Classifier: Programming Language :: Python :: 3.12
Classifier: Programming Language :: Python :: 3.13
Classifier: Programming Language :: Python :: 3.14
Classifier: Development Status :: 5 - Production/Stable
Classifier: Framework :: AsyncIO
Requires-Python: >=3.10
License-File: LICENSE
Requires-Dist: typing_extensions>=4.0.0; python_version < "3.11"
Dynamic: license-file
